HiNT/ArgsValidator.py
HiNT/BPsummarization.py
HiNT/DoRegressionAllchroms.py
HiNT/HiCprocessingPip.py
HiNT/__init__.py
HiNT/coolToMatrix.py
HiNT/corelib.py
HiNT/diff.py
HiNT/doBICseq.py
HiNT/getBPfromChimericReads.py
HiNT/getGenomeRowSumsFromCool.py
HiNT/getGenomeRowSumsFromHiC.py
HiNT/getRankProduct.py
HiNT/getRoughBreakpoints.py
HiNT/hicToMatrix.py
HiNT/prepare_regression.py
HiNT/read_hic_header.py
HiNT/runhint.py
HiNT/straw.py
HiNT/externalScripts/.Rapp.history
HiNT/externalScripts/extract_nonHiC.pl
HiNT/externalScripts/generate_site_positions.py
HiNT/externalScripts/getBreakPoints2steps.R
HiNT/externalScripts/plot.l2r.ms_zoom.R
HiNT_Package-2.2.8.data/scripts/hint
HiNT_Package-2.2.8.dist-info/METADATA
HiNT_Package-2.2.8.dist-info/WHEEL
HiNT_Package-2.2.8.dist-info/top_level.txt
HiNT_Package-2.2.8.dist-info/RECORD
