Metadata-Version: 2.1
Name: HiNT-Package
Version: 2.2.8
Summary: HiNT -- HiC for copy number vairations and translocations detection 
Home-page: https://github.com/suwangbio/HiNT_py3
Author: Su Wang
Author-email: wangsu0623@gmail.com
License: UNKNOWN
Platform: UNKNOWN
Classifier: Programming Language :: Python :: 3
Classifier: Environment :: Console
Classifier: Environment :: Web Environment
Classifier: Intended Audience :: Developers
Classifier: License :: OSI Approved :: MIT License
Classifier: Operating System :: MacOS :: MacOS X
Classifier: Operating System :: POSIX
Classifier: Topic :: Software Development
Requires-Dist: h5py (>=2.8.0)
Requires-Dist: numpy (>=1.16.1)
Requires-Dist: cooler (==0.8.3)
Requires-Dist: pypairix (>=0.3.0)
Requires-Dist: pairtools (>=0.2.2)
Requires-Dist: scipy (>=1.0.1)
Requires-Dist: pandas (>=0.23.0)
Requires-Dist: scikit-learn (>=0.19.1)
Requires-Dist: multiprocess (>=0.70.5)
Requires-Dist: argparse (>=1.1)
Requires-Dist: pytabix
